pdm_wheel-0.1.2.dist-info/METADATA
pdm_wheel-0.1.2.dist-info/WHEEL
pdm_wheel-0.1.2.dist-info/entry_points.txt
pdm_wheel-0.1.2.dist-info/licenses/LICENSE
pdm_wheel/__init__.py
pdm_wheel/_version.py
pdm_wheel/py.typed
pdm_wheel/wheel.py
pdm_wheel-0.1.2.dist-info/RECORD
