Metadata-Version: 2.1
Name: pdm-wheel
Version: 0.1.2
Summary: PDM plugin that save your requirements as wheels, similar to pip-wheel
Author-Email: Gabriel Dugny <pdm-wheel@dugny.me>
License: MIT
Classifier: Development Status :: 2 - Pre-Alpha
Classifier: Intended Audience :: Developers
Classifier: License :: OSI Approved :: MIT License
Classifier: Operating System :: OS Independent
Classifier: Programming Language :: Python
Classifier: Programming Language :: Python :: 3
Classifier: Programming Language :: Python :: 3 :: Only
Classifier: Programming Language :: Python :: 3.9
Classifier: Programming Language :: Python :: 3.10
Classifier: Programming Language :: Python :: 3.11
Classifier: Programming Language :: Python :: 3.12
Classifier: Typing :: Typed
Project-URL: Homepage, https://github.com/GabDug/pdm-wheel
Project-URL: Changelog, https://github.com/GabDug/pdm-wheel/blob/main/CHANGELOG.md
Project-URL: Bug tracker, https://github.com/GabDug/pdm-wheel/issues
Requires-Python: >=3.9
Provides-Extra: pdm
Requires-Dist: pdm>=2.7.4; extra == "pdm"
